AUTHORS
LICENSE
MANIFEST.in
requirements.txt
setup.cfg
setup.py
django_stashboard.egg-info/PKG-INFO
django_stashboard.egg-info/SOURCES.txt
django_stashboard.egg-info/dependency_links.txt
django_stashboard.egg-info/not-zip-safe
django_stashboard.egg-info/requires.txt
django_stashboard.egg-info/top_level.txt
stashboard/__init__.py
stashboard/admin.py
stashboard/api.py
stashboard/forms.py
stashboard/models.py
stashboard/serializers.py
stashboard/urls.py
stashboard/views.py
stashboard/fixtures/status.json
stashboard/migrations/0001_initial.py
stashboard/migrations/0002_auto_20141016_1206.py
stashboard/migrations/__init__.py
stashboard/static/favicon.ico
stashboard/static/css/font-awesome.css
stashboard/static/css/gh-buttons.css
stashboard/static/css/gh-icons.png
stashboard/static/css/prettify.css
stashboard/static/css/reset.css
stashboard/static/css/style.css
stashboard/static/font/fontawesome-webfont.eot
stashboard/static/font/fontawesome-webfont.svg
stashboard/static/font/fontawesome-webfont.ttf
stashboard/static/font/fontawesome-webfont.woff
stashboard/static/images/feed-icon-14x14.png
stashboard/static/images/logo.png
stashboard/static/images/mustacheman.png
stashboard/static/images/oauth_logo.jpg
stashboard/static/images/poweredbystash.png
stashboard/static/images/small-information.png
stashboard/static/images/sub-nav-selected-arrow.png
stashboard/static/images/icons/fugue/broom.png
stashboard/static/images/icons/fugue/bug.png
stashboard/static/images/icons/fugue/clock.png
stashboard/static/images/icons/fugue/cross-circle.png
stashboard/static/images/icons/fugue/exclamation.png
stashboard/static/images/icons/fugue/flag.png
stashboard/static/images/icons/fugue/hard-hat.png
stashboard/static/images/icons/fugue/heart.png
stashboard/static/images/icons/fugue/information-small.png
stashboard/static/images/icons/fugue/information-white.png
stashboard/static/images/icons/fugue/information.png
stashboard/static/images/icons/fugue/lock.png
stashboard/static/images/icons/fugue/plug.png
stashboard/static/images/icons/fugue/plus-circle.png
stashboard/static/images/icons/fugue/question-white.png
stashboard/static/images/icons/fugue/question.png
stashboard/static/images/icons/fugue/tick-circle.png
