Metadata-Version: 1.0
Name: django-stashboard
Version: 0.1dev.20141117.1520
Summary: Fork of Stashboard (GAE) modified for pure-django.
Home-page: https://github.com/goodtune/django-stashboard
Author: Gary Reynolds
Author-email: gary.j.reynolds@det.nsw.edu.au
License: UNKNOWN
Platform: UNKNOWN
